{
	"air": {
		"name": "Air",
		"version": 1000,
		"id": "air",
		"color": [0, 0, 0, 0]
	},
	"acacia_log": {
		"name": "Acacia Log",
		"version": 1072,
		"id": "acacia_log",
		"color": [104, 98, 88, 255]
	},
	"acacia_log_top": {
		"name": "Acacia Log (Top)",
		"version": 1072,
		"id": "acacia_log",
		"color": [156, 89, 56, 255],
		"properties": {
			"axis": "z"
		}
	},
	"acacia_planks": {
		"name": "Acacia Planks",
		"version": 1072,
		"id": "acacia_planks",
		"color": [169, 91, 51, 255]
	},
	"acacia_trapdoor": {
		"name": "Acacia Trapdoor",
		"version": 1130,
		"id": "acacia_trapdoor",
		"color": [160, 89, 53, 195],
		"properties": {
			"open": "true"
		}
	},
	"amethyst_block": {
		"name": "Block of Amethyst",
		"version": 1170,
		"id": "amethyst_block",
		"color": [139, 102, 194, 255]
	},
	"ancient_debris_side": {
		"name": "Ancient Debris",
		"version": 1160,
		"id": "ancient_debris",
		"color": [99, 70, 63, 255]
	},
	"andesite": {
		"name": "Andesite",
		"version": 1080,
		"id": "andesite",
		"color": [137, 137, 138, 255]
	},
	"bamboo_block": {
		"name": "Block of Bamboo",
		"version": 1200,
		"id": "bamboo_block",
		"color": [129, 146, 58, 255]
	},
	"bamboo_block_top": {
		"name": "Block of Bamboo (Top)",
		"version": 1200,
		"id": "bamboo_block",
		"color": [143, 145, 66, 255],
		"properties": {
			"axis": "z"
		}
	},
	"bamboo_mosaic": {
		"name": "Bamboo Mosaic",
		"version": 1200,
		"id": "bamboo_mosaic",
		"color": [192, 172, 79, 255]
	},
	"bamboo_planks": {
		"name": "Bamboo Planks",
		"version": 1200,
		"id": "bamboo_planks",
		"color": [195, 175, 82, 255]
	},
	"bamboo_trapdoor": {
		"name": "Bamboo Trapdoor",
		"version": 1200,
		"id": "bamboo_trapdoor",
		"color": [200, 181, 87, 211],
		"properties": {
			"open": "true"
		}
	},
	"barrel_bottom": {
		"name": "Barrel (Bottom)",
		"version": 1140,
		"id": "barrel",
		"color": [117, 86, 50, 255],
		"properties": {
			"facing": "north"
		}
	},
	"barrel_side": {
		"name": "Barrel",
		"version": 1140,
		"id": "barrel",
		"color": [115, 85, 52, 255],
		"properties": {
			"facing": "south"
		}
	},
	"barrel_top": {
		"name": "Barrel (Top)",
		"version": 1140,
		"id": "barrel",
		"color": [136, 101, 59, 255],
		"properties": {
			"facing": "up"
		}
	},
	"basalt_side": {
		"name": "Basalt",
		"version": 1160,
		"id": "basalt",
		"color": [75, 74, 79, 255]
	},
	"basalt_top": {
		"name": "Basalt (Top)",
		"version": 1160,
		"id": "basalt",
		"color": [85, 86, 89, 255],
		"properties": {
			"axis": "z"
		}
	},
	"bedrock": {
		"name": "Bedrock",
		"version": 1000,
		"id": "bedrock",
		"color": [93, 93, 93, 255],
		"creative": true
	},
	"bee_nest_front": {
		"name": "Bee Nest",
		"version": 1150,
		"id": "bee_nest",
		"color": [191, 151, 80, 255],
		"properties": {
			"facing": "south"
		}
	},
	"bee_nest_side": {
		"name": "Bee Nest (Side)",
		"version": 1150,
		"id": "bee_nest",
		"color": [201, 158, 81, 255]
	},
	"beehive_side": {
		"name": "Beehive (Side)",
		"version": 1150,
		"id": "beehive",
		"color": [160, 129, 79, 255]
	},
	"birch_log": {
		"name": "Birch Log",
		"version": 1020,
		"id": "birch_log",
		"color": [223, 222, 218, 255]
	},
	"birch_log_top": {
		"name": "Birch Log (Top)",
		"version": 1020,
		"id": "birch_log",
		"color": [196, 183, 141, 255],
		"properties": {
			"axis": "z"
		}
	},
	"birch_planks": {
		"name": "Birch Planks",
		"version": 1020,
		"id": "birch_planks",
		"color": [194, 177, 122, 255]
	},
	"birch_trapdoor": {
		"name": "Birch Trapdoor",
		"version": 1130,
		"id": "birch_trapdoor",
		"color": [211, 199, 166, 255],
		"properties": {
			"open": "true"
		}
	},
	"black_concrete": {
		"name": "Black Concrete",
		"version": 1120,
		"id": "black_concrete",
		"color": [8, 10, 15, 255]
	},
	"black_concrete_powder": {
		"name": "Black Concrete Powder",
		"version": 1120,
		"id": "black_concrete_powder",
		"color": [27, 28, 33, 255],
		"falling": true
	},
	"black_glazed_terracotta": {
		"name": "Black Glazed Terracotta",
		"version": 1120,
		"id": "black_glazed_terracotta",
		"color": [86, 34, 36, 255]
	},
	"black_shulker_box": {
		"name": "Black Shulker Box",
		"version": 1110,
		"id": "black_shulker_box",
		"color": [26, 26, 30, 255],
		"tile_entity": true,
		"properties": {
			"facing": "south"
		}
	},
	"black_stained_glass": {
		"name": "Black Stained Glass",
		"version": 1072,
		"id": "black_stained_glass",
		"color": [25, 25, 25, 117]
	},
	"black_terracotta": {
		"name": "Black Terracotta",
		"version": 1061,
		"id": "black_terracotta",
		"color": [37, 23, 16, 255]
	},
	"black_wool": {
		"name": "Black Wool",
		"version": 1020,
		"id": "black_wool",
		"color": [22, 23, 27, 255]
	},
	"blackstone": {
		"name": "Blackstone",
		"version": 1160,
		"id": "blackstone",
		"color": [44, 39, 45, 255]
	},
	"blast_furnace_front": {
		"name": "Blast Furnace",
		"version": 1140,
		"id": "blast_furnace",
		"color": [115, 115, 114, 255],
		"properties": {
			"facing": "south"
		}
	},
	"blast_furnace_side": {
		"name": "Blast Furnace (Side)",
		"version": 1140,
		"id": "blast_furnace",
		"color": [113, 113, 113, 255],
		"properties": {
			"facing": "north"
		}
	},
	"blue_concrete": {
		"name": "Blue Concrete",
		"version": 1120,
		"id": "blue_concrete",
		"color": [45, 47, 143, 255]
	},
	"blue_concrete_powder": {
		"name": "Blue Concrete Powder",
		"version": 1120,
		"id": "blue_concrete_powder",
		"color": [70, 74, 167, 255],
		"falling": true
	},
	"blue_glazed_terracotta": {
		"name": "Blue Glazed Terracotta",
		"version": 1120,
		"id": "blue_glazed_terracotta",
		"color": [49, 75, 150, 255]
	},
	"blue_ice": {
		"name": "Blue Ice",
		"version": 1130,
		"id": "blue_ice",
		"color": [117, 168, 253, 255]
	},
	"blue_shulker_box": {
		"name": "Blue Shulker Box",
		"version": 1110,
		"id": "blue_shulker_box",
		"color": [44, 46, 141, 255],
		"tile_entity": true,
		"properties": {
			"facing": "south"
		}
	},
	"blue_stained_glass": {
		"name": "Blue Stained Glass",
		"version": 1072,
		"id": "blue_stained_glass",
		"color": [51, 76, 178, 117]
	},
	"blue_terracotta": {
		"name": "Blue Terracotta",
		"version": 1061,
		"id": "blue_terracotta",
		"color": [74, 60, 91, 255]
	},
	"blue_wool": {
		"name": "Blue Wool",
		"version": 1020,
		"id": "blue_wool",
		"color": [53, 58, 158, 255]
	},
	"bone_block_side": {
		"name": "Bone Block",
		"version": 1100,
		"id": "bone_block",
		"color": [229, 226, 208, 255]
	},
	"bone_block_top": {
		"name": "Bone Block (Top)",
		"version": 1100,
		"id": "bone_block",
		"color": [210, 207, 180, 255],
		"properties": {
			"axis": "z"
		}
	},
	"bookshelf": {
		"name": "Bookshelf",
		"version": 1000,
		"id": "bookshelf",
		"color": [131, 106, 75, 255]
	},
	"brain_coral_block": {
		"name": "Brain Coral Block",
		"version": 1130,
		"id": "brain_coral_block",
		"color": [208, 95, 161, 255],
		"creative": true
	},
	"bricks": {
		"name": "Bricks",
		"version": 1000,
		"id": "bricks",
		"color": [152, 101, 88, 255]
	},
	"brown_concrete": {
		"name": "Brown Concrete",
		"version": 1120,
		"id": "brown_concrete",
		"color": [96, 60, 32, 255]
	},
	"brown_concrete_powder": {
		"name": "Brown Concrete Powder",
		"version": 1120,
		"id": "brown_concrete_powder",
		"color": [126, 85, 54, 255],
		"falling": true
	},
	"brown_glazed_terracotta": {
		"name": "Brown Glazed Terracotta",
		"version": 1120,
		"id": "brown_glazed_terracotta",
		"color": [135, 110, 95, 255]
	},
	"brown_mushroom_block": {
		"name": "Brown Mushroom Block",
		"version": 1080,
		"id": "brown_mushroom_block",
		"color": [149, 112, 81, 255]
	},
	"brown_shulker_box": {
		"name": "Brown Shulker Box",
		"version": 1110,
		"id": "brown_shulker_box",
		"color": [107, 66, 36, 255],
		"tile_entity": true,
		"properties": {
			"facing": "south"
		}
	},
	"brown_stained_glass": {
		"name": "Brown Stained Glass",
		"version": 1072,
		"id": "brown_stained_glass",
		"color": [102, 76, 51, 117]
	},
	"brown_terracotta": {
		"name": "Brown Terracotta",
		"version": 1061,
		"id": "brown_terracotta",
		"color": [77, 51, 36, 255]
	},
	"brown_wool": {
		"name": "Brown Wool",
		"version": 1020,
		"id": "brown_wool",
		"color": [115, 72, 41, 255]
	},
	"bubble_coral_block": {
		"name": "Bubble Coral Block",
		"version": 1130,
		"id": "bubble_coral_block",
		"color": [168, 29, 163, 255],
		"creative": true
	},
	"budding_amethyst": {
		"name": "Budding Amethyst",
		"version": 1170,
		"id": "budding_amethyst",
		"color": [140, 103, 190, 255]
	},
	"calcite": {
		"name": "Calcite",
		"version": 1170,
		"id": "calcite",
		"color": [224, 225, 222, 255]
	},
	"cartography_table_side1": {
		"name": "Cartography Table",
		"version": 1140,
		"id": "cartography_table",
		"color": [96, 77, 69, 255]
	},
	"carved_pumpkin": {
		"name": "Carved Pumpkin",
		"version": 1000,
		"id": "carved_pumpkin",
		"color": [165, 101, 25, 255]
	},
	"cauldron_side": {
		"name": "Cauldron",
		"version": 1000,
		"id": "cauldron",
		"color": [76, 75, 76, 255]
	},
	"chain_command_block_front": {
		"name": "Chain Command Block",
		"version": 1042,
		"id": "chain_command_block",
		"color": [138, 170, 156, 255],
		"creative": true,
		"properties": {
			"facing": "south"
		}
	},
	"cherry_log": {
		"name": "Cherry Log",
		"version": 1200,
		"id": "cherry_log",
		"color": [56, 34, 45, 255]
	},
	"cherry_log_top": {
		"name": "Cherry Log (Top)",
		"version": 1200,
		"id": "cherry_log",
		"color": [200, 155, 148, 255],
		"properties": {
			"axis": "z"
		}
	},
	"cherry_planks": {
		"name": "Cherry Planks",
		"version": 1200,
		"id": "cherry_planks",
		"color": [227, 180, 174, 255]
	},
	"cherry_trapdoor": {
		"name": "Cherry Trapdoor",
		"version": 1200,
		"id": "cherry_trapdoor",
		"color": [227, 180, 173, 219],
		"properties": {
			"open": "true"
		}
	},
	"chiseled_bookshelf_empty": {
		"name": "Chiseled Bookshelf (Empty)",
		"version": 1200,
		"id": "chiseled_bookshelf",
		"color": [111, 88, 53, 255],
		"properties": {
			"facing": "south"
		}
	},
	"chiseled_bookshelf_occupied": {
		"name": "Chiseled Bookshelf (Full)",
		"version": 1200,
		"id": "chiseled_bookshelf",
		"color": [138, 106, 82, 255],
		"properties": {
			"facing": "south",
			"slot_0_occupied": "true",
			"slot_1_occupied": "true",
			"slot_2_occupied": "true",
			"slot_3_occupied": "true",
			"slot_4_occupied": "true",
			"slot_5_occupied": "true"
		}
	},
	"chiseled_bookshelf_side": {
		"name": "Chiseled Bookshelf (Side)",
		"version": 1200,
		"id": "chiseled_bookshelf",
		"color": [176, 143, 88, 255],
		"properties": {
			"facing": "east"
		}
	},
	"chiseled_copper": {
		"name": "Chiseled Copper",
		"version": 1210,
		"id": "chiseled_copper",
		"color": [186, 102, 76, 255]
	},
	"chiseled_deepslate": {
		"name": "Chiseled Deepslate",
		"version": 1170,
		"id": "chiseled_deepslate",
		"color": [57, 57, 57, 255]
	},
	"chiseled_nether_bricks": {
		"name": "Chiseled Nether Bricks",
		"version": 1160,
		"id": "chiseled_nether_bricks",
		"color": [48, 24, 29, 255]
	},
	"chiseled_polished_blackstone": {
		"name": "Chiseled Polished Blackstone",
		"version": 1160,
		"id": "chiseled_polished_blackstone",
		"color": [57, 53, 61, 255]
	},
	"chiseled_quartz_block": {
		"name": "Chiseled Quartz Block",
		"version": 1050,
		"id": "chiseled_quartz_block",
		"color": [232, 227, 218, 255]
	},
	"chiseled_red_sandstone": {
		"name": "Chiseled Red Sandstone",
		"version": 1080,
		"id": "chiseled_red_sandstone",
		"color": [184, 98, 30, 255]
	},
	"chiseled_resin_bricks": {
		"name": "Chiseled Resin Bricks",
		"version": 1214,
		"id": "chiseled_resin_bricks",
		"color": [203, 90, 29, 255]
	},
	"chiseled_sandstone": {
		"name": "Chiseled Sandstone",
		"version": 1024,
		"id": "chiseled_sandstone",
		"color": [217, 204, 158, 255]
	},
	"chiseled_stone_bricks": {
		"name": "Chiseled Stone Bricks",
		"version": 1020,
		"id": "chiseled_stone_bricks",
		"color": [122, 121, 122, 255]
	},
	"chiseled_tuff": {
		"name": "Chiseled Tuff",
		"version": 1210,
		"id": "chiseled_tuff",
		"color": [92, 96, 89, 255]
	},
	"chiseled_tuff_bricks": {
		"name": "Chiseled Tuff Bricks",
		"version": 1210,
		"id": "chiseled_tuff_bricks",
		"color": [101, 105, 98, 255]
	},
	"clay": {
		"name": "Clay",
		"version": 1000,
		"id": "clay",
		"color": [161, 167, 180, 255]
	},
	"coal_block": {
		"name": "Block of Coal",
		"version": 1061,
		"id": "coal_block",
		"color": [18, 18, 18, 255]
	},
	"coal_ore": {
		"name": "Coal Ore",
		"version": 1000,
		"id": "coal_ore",
		"color": [110, 110, 110, 255]
	},
	"coarse_dirt": {
		"name": "Coarse Dirt",
		"version": 1072,
		"id": "coarse_dirt",
		"color": [124, 89, 62, 255]
	},
	"cobbled_deepslate": {
		"name": "Cobbled Deepslate",
		"version": 1170,
		"id": "cobbled_deepslate",
		"color": [80, 80, 83, 255]
	},
	"cobblestone": {
		"name": "Cobblestone",
		"version": 1000,
		"id": "cobblestone",
		"color": [131, 131, 131, 255]
	},
	"cobweb": {
		"name": "Cobweb",
		"version": 1050,
		"id": "cobweb",
		"color": [230, 234, 235, 105]
	},
	"command_block_front": {
		"name": "Command Block",
		"version": 1042,
		"id": "command_block",
		"color": [185, 141, 120, 255],
		"creative": true,
		"properties": {
			"facing": "south"
		}
	},
	"composter_side": {
		"name": "Composter",
		"version": 1140,
		"id": "composter",
		"color": [118, 76, 38, 255]
	},
	"copper_block": {
		"name": "Block of Copper",
		"version": 1170,
		"id": "copper_block",
		"color": [194, 109, 81, 255]
	},
	"copper_bulb": {
		"name": "Copper Bulb",
		"version": 1210,
		"id": "copper_bulb",
		"color": [163, 91, 64, 255]
	},
	"copper_bulb_lit": {
		"name": "Copper Bulb (Lit)",
		"version": 1210,
		"id": "copper_bulb",
		"color": [219, 162, 118, 255],
		"properties": {
			"lit": "true"
		}
	},
	"copper_grate": {
		"name": "Copper Grate",
		"version": 1210,
		"id": "copper_grate",
		"color": [193, 109, 81, 178]
	},
	"copper_ore": {
		"name": "Copper Ore",
		"version": 1170,
		"id": "copper_ore",
		"color": [129, 127, 122, 255]
	},
	"copper_trapdoor": {
		"name": "Copper Trapdoor",
		"version": 1210,
		"id": "copper_trapdoor",
		"color": [193, 108, 82, 203],
		"properties": {
			"open": "true"
		}
	},
	"cracked_deepslate_bricks": {
		"name": "Cracked Deepslate Bricks",
		"version": 1170,
		"id": "cracked_deepslate_bricks",
		"color": [69, 69, 69, 255]
	},
	"cracked_deepslate_tiles": {
		"name": "Cracked Deepslate Tiles",
		"version": 1170,
		"id": "cracked_deepslate_tiles",
		"color": [55, 55, 55, 255]
	},
	"cracked_nether_bricks": {
		"name": "Cracked Nether Bricks",
		"version": 1160,
		"id": "cracked_nether_bricks",
		"color": [43, 21, 25, 255]
	},
	"cracked_polished_blackstone_bricks": {
		"name": "Cracked Polished Blackstone Bricks",
		"version": 1160,
		"id": "cracked_polished_blackstone_bricks",
		"color": [47, 42, 49, 255]
	},
	"cracked_stone_bricks": {
		"name": "Cracked Stone Bricks",
		"version": 1000,
		"id": "cracked_stone_bricks",
		"color": [120, 119, 120, 255]
	},
	"crafter_bottom": {
		"name": "Crafter (Bottom)",
		"version": 1200,
		"id": "crafter",
		"color": [80, 80, 80, 255],
		"properties": {
			"orientation": "up_north"
		}
	},
	"crafter_north": {
		"name": "Crafter",
		"version": 1200,
		"id": "crafter",
		"color": [120, 114, 107, 255],
		"properties": {
			"orientation": "south_up"
		}
	},
	"crafter_south": {
		"name": "Crafter (South)",
		"version": 1200,
		"id": "crafter",
		"color": [129, 118, 104, 255],
		"properties": {
			"orientation": "north_up"
		}
	},
	"crafter_top": {
		"name": "Crafter (Top)",
		"version": 1200,
		"id": "crafter",
		"color": [118, 112, 113, 255],
		"properties": {
			"orientation": "up_south"
		}
	},
	"crafter_west": {
		"name": "Crafter (West)",
		"version": 1200,
		"id": "crafter",
		"color": [136, 122, 103, 255],
		"properties": {
			"orientation": "west_up"
		}
	},
	"crafting_table_front": {
		"name": "Crafting Table",
		"version": 1000,
		"id": "crafting_table",
		"color": [145, 122, 89, 255]
	},
	"creaking_heart": {
		"name": "Creaking Heart",
		"version": 1214,
		"id": "creaking_heart",
		"color": [86, 73, 68, 255]
	},
	"crimson_nylium_side": {
		"name": "Crimson Nylium",
		"version": 1160,
		"id": "crimson_nylium",
		"color": [111, 33, 33, 255],
		"creative": true
	},
	"crimson_planks": {
		"name": "Crimson Planks",
		"version": 1160,
		"id": "crimson_planks",
		"color": [104, 50, 72, 255]
	},
	"crimson_stem": {
		"name": "Crimson Stem",
		"version": 1160,
		"id": "crimson_stem",
		"color": [97, 29, 37, 255]
	},
	"crimson_stem_top": {
		"name": "Crimson Stem (Top)",
		"version": 1160,
		"id": "crimson_stem",
		"color": [115, 51, 74, 255],
		"properties": {
			"axis": "z"
		}
	},
	"crimson_trapdoor": {
		"name": "Crimson Trapdoor",
		"version": 1160,
		"id": "crimson_trapdoor",
		"color": [107, 52, 74, 215],
		"properties": {
			"open": "true"
		}
	},
	"crying_obsidian": {
		"name": "Crying Obsidian",
		"version": 1160,
		"id": "crying_obsidian",
		"color": [48, 16, 88, 255]
	},
	"cut_copper": {
		"name": "Cut Copper",
		"version": 1170,
		"id": "cut_copper",
		"color": [193, 108, 83, 255]
	},
	"cut_red_sandstone": {
		"name": "Cut Red Sandstone",
		"version": 1080,
		"id": "cut_red_sandstone",
		"color": [190, 102, 33, 255]
	},
	"cut_sandstone": {
		"name": "Cut Sandstone",
		"version": 1024,
		"id": "cut_sandstone",
		"color": [218, 207, 161, 255]
	},
	"cyan_concrete": {
		"name": "Cyan Concrete",
		"version": 1120,
		"id": "cyan_concrete",
		"color": [21, 119, 136, 255]
	},
	"cyan_concrete_powder": {
		"name": "Cyan Concrete Powder",
		"version": 1120,
		"id": "cyan_concrete_powder",
		"color": [37, 148, 157, 255],
		"falling": true
	},
	"cyan_glazed_terracotta": {
		"name": "Cyan Glazed Terracotta",
		"version": 1120,
		"id": "cyan_glazed_terracotta",
		"color": [74, 128, 134, 255]
	},
	"cyan_shulker_box": {
		"name": "Cyan Shulker Box",
		"version": 1110,
		"id": "cyan_shulker_box",
		"color": [20, 122, 136, 255],
		"tile_entity": true,
		"properties": {
			"facing": "south"
		}
	},
	"cyan_stained_glass": {
		"name": "Cyan Stained Glass",
		"version": 1072,
		"id": "cyan_stained_glass",
		"color": [76, 127, 153, 117]
	},
	"cyan_terracotta": {
		"name": "Cyan Terracotta",
		"version": 1061,
		"id": "cyan_terracotta",
		"color": [87, 91, 91, 255]
	},
	"cyan_wool": {
		"name": "Cyan Wool",
		"version": 1020,
		"id": "cyan_wool",
		"color": [21, 138, 145, 255]
	},
	"dark_oak_log": {
		"name": "Dark Oak Log",
		"version": 1072,
		"id": "dark_oak_log",
		"color": [61, 47, 27, 255]
	},
	"dark_oak_log_top": {
		"name": "Dark Oak Log (Top)",
		"version": 1072,
		"id": "dark_oak_log",
		"color": [68, 46, 23, 255],
		"properties": {
			"axis": "z"
		}
	},
	"dark_oak_planks": {
		"name": "Dark Oak Planks",
		"version": 1072,
		"id": "dark_oak_planks",
		"color": [68, 44, 21, 255]
	},
	"dark_oak_trapdoor": {
		"name": "Dark Oak Trapdoor",
		"version": 1130,
		"id": "dark_oak_trapdoor",
		"color": [78, 51, 24, 255],
		"properties": {
			"open": "true"
		}
	},
	"dark_prismarine": {
		"name": "Dark Prismarine",
		"version": 1080,
		"id": "dark_prismarine",
		"color": [53, 95, 78, 255]
	},
	"dead_brain_coral_block": {
		"name": "Dead Brain Coral Block",
		"version": 1130,
		"id": "dead_brain_coral_block",
		"color": [126, 119, 116, 255]
	},
	"dead_bubble_coral_block": {
		"name": "Dead Bubble Coral Block",
		"version": 1130,
		"id": "dead_bubble_coral_block",
		"color": [133, 125, 121, 255]
	},
	"dead_horn_coral_block": {
		"name": "Dead Horn Coral Block",
		"version": 1130,
		"id": "dead_horn_coral_block",
		"color": [136, 128, 124, 255]
	},
	"dead_tube_coral_block": {
		"name": "Dead Tube Coral Block",
		"version": 1130,
		"id": "dead_tube_coral_block",
		"color": [132, 125, 121, 255]
	},
	"deepslate": {
		"name": "Deepslate",
		"version": 1170,
		"id": "deepslate",
		"color": [83, 83, 85, 255]
	},
	"deepslate_bricks": {
		"name": "Deepslate Bricks",
		"version": 1170,
		"id": "deepslate_bricks",
		"color": [74, 74, 75, 255]
	},
	"deepslate_coal_ore": {
		"name": "Deepslate Coal Ore",
		"version": 1170,
		"id": "deepslate_coal_ore",
		"color": [80, 80, 81, 255]
	},
	"deepslate_copper_ore": {
		"name": "Deepslate Copper Ore",
		"version": 1170,
		"id": "deepslate_copper_ore",
		"color": [100, 98, 92, 255]
	},
	"deepslate_diamond_ore": {
		"name": "Deepslate Diamond Ore",
		"version": 1170,
		"id": "deepslate_diamond_ore",
		"color": [89, 117, 116, 255]
	},
	"deepslate_emerald_ore": {
		"name": "Deepslate Emerald Ore",
		"version": 1170,
		"id": "deepslate_emerald_ore",
		"color": [88, 117, 95, 255]
	},
	"deepslate_gold_ore": {
		"name": "Deepslate Gold Ore",
		"version": 1170,
		"id": "deepslate_gold_ore",
		"color": [130, 112, 85, 255]
	},
	"deepslate_iron_ore": {
		"name": "Deepslate Iron Ore",
		"version": 1170,
		"id": "deepslate_iron_ore",
		"color": [116, 105, 98, 255]
	},
	"deepslate_lapis_ore": {
		"name": "Deepslate Lapis Lazuli Ore",
		"version": 1170,
		"id": "deepslate_lapis_ore",
		"color": [86, 94, 125, 255]
	},
	"deepslate_redstone_ore": {
		"name": "Deepslate Redstone Ore",
		"version": 1170,
		"id": "deepslate_redstone_ore",
		"color": [117, 80, 81, 255]
	},
	"deepslate_tiles": {
		"name": "Deepslate Tiles",
		"version": 1170,
		"id": "deepslate_tiles",
		"color": [57, 57, 57, 255]
	},
	"deepslate_top": {
		"name": "Deepslate (Top)",
		"version": 1170,
		"id": "deepslate",
		"color": [89, 89, 91, 255],
		"properties": {
			"axis": "z"
		}
	},
	"diamond_block": {
		"name": "Block of Diamond",
		"version": 1000,
		"id": "diamond_block",
		"color": [110, 238, 229, 255]
	},
	"diamond_ore": {
		"name": "Diamond Ore",
		"version": 1000,
		"id": "diamond_ore",
		"color": [125, 146, 144, 255]
	},
	"diorite": {
		"name": "Diorite",
		"version": 1080,
		"id": "diorite",
		"color": [192, 192, 192, 255]
	},
	"dirt": {
		"name": "Dirt",
		"version": 1000,
		"id": "dirt",
		"color": [137, 99, 69, 255]
	},
	"dispenser_front": {
		"name": "Dispenser",
		"version": 1020,
		"id": "dispenser",
		"color": [131, 130, 130, 255],
		"properties": {
			"facing": "south"
		}
	},
	"dried_kelp_side": {
		"name": "Dried Kelp Block",
		"version": 1130,
		"id": "dried_kelp_block",
		"color": [47, 55, 38, 255]
	},
	"dripstone_block": {
		"name": "Dripstone Block",
		"version": 1170,
		"id": "dripstone_block",
		"color": [136, 110, 93, 255]
	},
	"dropper_front": {
		"name": "Dropper",
		"version": 1050,
		"id": "dropper",
		"color": [131, 131, 131, 255],
		"properties": {
			"facing": "south"
		}
	},
	"emerald_block": {
		"name": "Block of Emerald",
		"version": 1031,
		"id": "emerald_block",
		"color": [55, 206, 97, 255]
	},
	"emerald_ore": {
		"name": "Emerald Ore",
		"version": 1031,
		"id": "emerald_ore",
		"color": [117, 141, 121, 255]
	},
	"end_stone": {
		"name": "End Stone",
		"version": 1000,
		"id": "end_stone",
		"color": [220, 224, 159, 255]
	},
	"end_stone_bricks": {
		"name": "End Stone Bricks",
		"version": 1090,
		"id": "end_stone_bricks",
		"color": [219, 226, 164, 255]
	},
	"exposed_chiseled_copper": {
		"name": "Exposed Chiseled Copper",
		"version": 1210,
		"id": "exposed_chiseled_copper",
		"color": [157, 120, 102, 255]
	},
	"exposed_copper": {
		"name": "Exposed Copper",
		"version": 1170,
		"id": "exposed_copper",
		"color": [163, 126, 105, 255]
	},
	"exposed_copper_bulb": {
		"name": "Exposed Copper Bulb",
		"version": 1210,
		"id": "exposed_copper_bulb",
		"color": [141, 110, 92, 255]
	},
	"exposed_copper_bulb_lit": {
		"name": "Exposed Copper Bulb (Lit)",
		"version": 1210,
		"id": "exposed_copper_bulb",
		"color": [200, 150, 107, 255],
		"properties": {
			"lit": "true"
		}
	},
	"exposed_copper_grate": {
		"name": "Exposed Copper Grate",
		"version": 1210,
		"id": "exposed_copper_grate",
		"color": [164, 127, 106, 178]
	},
	"exposed_copper_trapdoor": {
		"name": "Exposed Copper Trapdoor",
		"version": 1210,
		"id": "exposed_copper_trapdoor",
		"color": [164, 126, 106, 203],
		"properties": {
			"open": "true"
		}
	},
	"exposed_cut_copper": {
		"name": "Exposed Cut Copper",
		"version": 1170,
		"id": "exposed_cut_copper",
		"color": [157, 123, 102, 255]
	},
	"fletching_table_front": {
		"name": "Fletching Table",
		"version": 1140,
		"id": "fletching_table",
		"color": [181, 164, 121, 255]
	},
	"furnace_front": {
		"name": "Furnace",
		"version": 1000,
		"id": "furnace",
		"color": [106, 106, 106, 255],
		"properties": {
			"facing": "south"
		}
	},
	"furnace_side": {
		"name": "Furnace (Side)",
		"version": 1000,
		"id": "furnace",
		"color": [126, 126, 126, 255],
		"properties": {
			"facing": "north"
		}
	},
	"gilded_blackstone": {
		"name": "Gilded Blackstone",
		"version": 1160,
		"id": "gilded_blackstone",
		"color": [69, 54, 44, 255]
	},
	"glass": {
		"name": "Glass",
		"version": 1000,
		"id": "glass",
		"color": [179, 215, 220, 65]
	},
	"glowstone": {
		"name": "Glowstone",
		"version": 1000,
		"id": "glowstone",
		"color": [181, 147, 106, 255]
	},
	"gold_block": {
		"name": "Block of Gold",
		"version": 1000,
		"id": "gold_block",
		"color": [247, 210, 68, 255]
	},
	"gold_ore": {
		"name": "Gold Ore",
		"version": 1000,
		"id": "gold_ore",
		"color": [151, 138, 115, 255]
	},
	"granite": {
		"name": "Granite",
		"version": 1080,
		"id": "granite",
		"color": [151, 105, 88, 255]
	},
	"grass_block_side": {
		"name": "Grass Block",
		"version": 1000,
		"id": "grass_block",
		"color": [130, 114, 68, 255]
	},
	"grass_block_snow": {
		"name": "Grass Block (Snow)",
		"version": 1000,
		"id": "grass_block",
		"color": [178, 168, 159, 255],
		"creative": true,
		"properties": {
			"snowy": "true"
		}
	},
	"gravel": {
		"name": "Gravel",
		"version": 1000,
		"id": "gravel",
		"color": [133, 129, 128, 255],
		"falling": true
	},
	"gray_concrete": {
		"name": "Gray Concrete",
		"version": 1120,
		"id": "gray_concrete",
		"color": [55, 58, 62, 255]
	},
	"gray_concrete_powder": {
		"name": "Gray Concrete Powder",
		"version": 1120,
		"id": "gray_concrete_powder",
		"color": [77, 81, 85, 255],
		"falling": true
	},
	"gray_glazed_terracotta": {
		"name": "Gray Glazed Terracotta",
		"version": 1120,
		"id": "gray_glazed_terracotta",
		"color": [90, 96, 99, 255]
	},
	"gray_shulker_box": {
		"name": "Gray Shulker Box",
		"version": 1110,
		"id": "gray_shulker_box",
		"color": [56, 59, 63, 255],
		"tile_entity": true,
		"properties": {
			"facing": "south"
		}
	},
	"gray_stained_glass": {
		"name": "Gray Stained Glass",
		"version": 1072,
		"id": "gray_stained_glass",
		"color": [76, 76, 76, 117]
	},
	"gray_terracotta": {
		"name": "Gray Terracotta",
		"version": 1061,
		"id": "gray_terracotta",
		"color": [58, 42, 36, 255]
	},
	"gray_wool": {
		"name": "Gray Wool",
		"version": 1020,
		"id": "gray_wool",
		"color": [63, 69, 72, 255]
	},
	"green_concrete": {
		"name": "Green Concrete",
		"version": 1120,
		"id": "green_concrete",
		"color": [73, 91, 36, 255]
	},
	"green_concrete_powder": {
		"name": "Green Concrete Powder",
		"version": 1120,
		"id": "green_concrete_powder",
		"color": [97, 119, 45, 255],
		"falling": true
	},
	"green_glazed_terracotta": {
		"name": "Green Glazed Terracotta",
		"version": 1120,
		"id": "green_glazed_terracotta",
		"color": [125, 148, 94, 255]
	},
	"green_shulker_box": {
		"name": "Green Shulker Box",
		"version": 1110,
		"id": "green_shulker_box",
		"color": [79, 101, 32, 255],
		"tile_entity": true,
		"properties": {
			"facing": "south"
		}
	},
	"green_stained_glass": {
		"name": "Green Stained Glass",
		"version": 1072,
		"id": "green_stained_glass",
		"color": [102, 127, 51, 117]
	},
	"green_terracotta": {
		"name": "Green Terracotta",
		"version": 1061,
		"id": "green_terracotta",
		"color": [76, 83, 42, 255]
	},
	"green_wool": {
		"name": "Green Wool",
		"version": 1020,
		"id": "green_wool",
		"color": [85, 110, 28, 255]
	},
	"hay_block_side": {
		"name": "Hay Bale",
		"version": 1061,
		"id": "hay_block",
		"color": [168, 140, 39, 255]
	},
	"hay_block_top": {
		"name": "Hay Bale (Top)",
		"version": 1061,
		"id": "hay_block",
		"color": [167, 140, 13, 255],
		"properties": {
			"axis": "z"
		}
	},
	"honey_block_side": {
		"name": "Honey Block",
		"version": 1150,
		"id": "honey_block",
		"color": [251, 190, 69, 189]
	},
	"honeycomb_block": {
		"name": "Honeycomb Block",
		"version": 1150,
		"id": "honeycomb_block",
		"color": [230, 153, 49, 255]
	},
	"horn_coral_block": {
		"name": "Horn Coral Block",
		"version": 1130,
		"id": "horn_coral_block",
		"color": [217, 202, 67, 255],
		"creative": true
	},
	"ice": {
		"name": "Ice",
		"version": 1000,
		"id": "ice",
		"color": [146, 184, 254, 190]
	},
	"iron_block": {
		"name": "Block of Iron",
		"version": 1000,
		"id": "iron_block",
		"color": [221, 221, 221, 255]
	},
	"iron_ore": {
		"name": "Iron Ore",
		"version": 1000,
		"id": "iron_ore",
		"color": [139, 131, 124, 255]
	},
	"jigsaw_top": {
		"name": "Jigsaw",
		"version": 1140,
		"id": "jigsaw",
		"color": [111, 96, 111, 255],
		"creative": true,
		"properties": {
			"orientation": "south_up"
		}
	},
	"jungle_log": {
		"name": "Jungle Log",
		"version": 1021,
		"id": "jungle_log",
		"color": [87, 69, 26, 255]
	},
	"jungle_log_top": {
		"name": "Jungle Log (Top)",
		"version": 1021,
		"id": "jungle_log",
		"color": [154, 112, 76, 255],
		"properties": {
			"axis": "z"
		}
	},
	"jungle_planks": {
		"name": "Jungle Planks",
		"version": 1021,
		"id": "jungle_planks",
		"color": [163, 117, 83, 255]
	},
	"jungle_trapdoor": {
		"name": "Jungle Trapdoor",
		"version": 1130,
		"id": "jungle_trapdoor",
		"color": [156, 113, 80, 213],
		"properties": {
			"open": "true"
		}
	},
	"lapis_block": {
		"name": "Block of Lapis Lazuli",
		"version": 1020,
		"id": "lapis_block",
		"color": [31, 68, 141, 255]
	},
	"lapis_ore": {
		"name": "Lapis Lazuli Ore",
		"version": 1020,
		"id": "lapis_ore",
		"color": [115, 121, 146, 255]
	},
	"light_blue_concrete": {
		"name": "Light Blue Concrete",
		"version": 1120,
		"id": "light_blue_concrete",
		"color": [36, 137, 199, 255]
	},
	"light_blue_concrete_powder": {
		"name": "Light Blue Concrete Powder",
		"version": 1120,
		"id": "light_blue_concrete_powder",
		"color": [75, 181, 213, 255],
		"falling": true
	},
	"light_blue_glazed_terracotta": {
		"name": "Light Blue Glazed Terracotta",
		"version": 1120,
		"id": "light_blue_glazed_terracotta",
		"color": [122, 177, 212, 255]
	},
	"light_blue_shulker_box": {
		"name": "Light Blue Shulker Box",
		"version": 1110,
		"id": "light_blue_shulker_box",
		"color": [50, 165, 212, 255],
		"tile_entity": true,
		"properties": {
			"facing": "south"
		}
	},
	"light_blue_stained_glass": {
		"name": "Light Blue Stained Glass",
		"version": 1072,
		"id": "light_blue_stained_glass",
		"color": [102, 153, 216, 117]
	},
	"light_blue_terracotta": {
		"name": "Light Blue Terracotta",
		"version": 1061,
		"id": "light_blue_terracotta",
		"color": [114, 109, 138, 255]
	},
	"light_blue_wool": {
		"name": "Light Blue Wool",
		"version": 1020,
		"id": "light_blue_wool",
		"color": [59, 176, 218, 255]
	},
	"light_gray_concrete": {
		"name": "Light Gray Concrete",
		"version": 1120,
		"id": "light_gray_concrete",
		"color": [125, 125, 115, 255]
	},
	"light_gray_concrete_powder": {
		"name": "Light Gray Concrete Powder",
		"version": 1120,
		"id": "light_gray_concrete_powder",
		"color": [155, 155, 149, 255],
		"falling": true
	},
	"light_gray_glazed_terracotta": {
		"name": "Light Gray Glazed Terracotta",
		"version": 1120,
		"id": "light_gray_glazed_terracotta",
		"color": [157, 171, 172, 255]
	},
	"light_gray_shulker_box": {
		"name": "Light Gray Shulker Box",
		"version": 1110,
		"id": "light_gray_shulker_box",
		"color": [126, 126, 117, 255],
		"tile_entity": true,
		"properties": {
			"facing": "south"
		}
	},
	"light_gray_stained_glass": {
		"name": "Light Gray Stained Glass",
		"version": 1072,
		"id": "light_gray_stained_glass",
		"color": [153, 153, 153, 117]
	},
	"light_gray_terracotta": {
		"name": "Light Gray Terracotta",
		"version": 1061,
		"id": "light_gray_terracotta",
		"color": [135, 107, 98, 255]
	},
	"light_gray_wool": {
		"name": "Light Gray Wool",
		"version": 1020,
		"id": "light_gray_wool",
		"color": [142, 142, 135, 255]
	},
	"lime_concrete": {
		"name": "Lime Concrete",
		"version": 1120,
		"id": "lime_concrete",
		"color": [94, 169, 25, 255]
	},
	"lime_concrete_powder": {
		"name": "Lime Concrete Powder",
		"version": 1120,
		"id": "lime_concrete_powder",
		"color": [126, 189, 42, 255],
		"falling": true
	},
	"lime_glazed_terracotta": {
		"name": "Lime Glazed Terracotta",
		"version": 1120,
		"id": "lime_glazed_terracotta",
		"color": [174, 200, 75, 255]
	},
	"lime_shulker_box": {
		"name": "Lime Shulker Box",
		"version": 1110,
		"id": "lime_shulker_box",
		"color": [101, 174, 23, 255],
		"tile_entity": true,
		"properties": {
			"facing": "south"
		}
	},
	"lime_stained_glass": {
		"name": "Lime Stained Glass",
		"version": 1072,
		"id": "lime_stained_glass",
		"color": [127, 204, 25, 117]
	},
	"lime_terracotta": {
		"name": "Lime Terracotta",
		"version": 1061,
		"id": "lime_terracotta",
		"color": [104, 118, 53, 255]
	},
	"lime_wool": {
		"name": "Lime Wool",
		"version": 1020,
		"id": "lime_wool",
		"color": [113, 185, 26, 255]
	},
	"lodestone_side": {
		"name": "Lodestone",
		"version": 1160,
		"id": "lodestone",
		"color": [124, 125, 128, 255]
	},
	"loom_front": {
		"name": "Loom",
		"version": 1140,
		"id": "loom",
		"color": [154, 125, 89, 255],
		"properties": {
			"facing": "south"
		}
	},
	"loom_side": {
		"name": "Loom (Side)",
		"version": 1140,
		"id": "loom",
		"color": [150, 108, 75, 255],
		"properties": {
			"facing": "east"
		}
	},
	"magenta_concrete": {
		"name": "Magenta Concrete",
		"version": 1120,
		"id": "magenta_concrete",
		"color": [169, 48, 159, 255]
	},
	"magenta_concrete_powder": {
		"name": "Magenta Concrete Powder",
		"version": 1120,
		"id": "magenta_concrete_powder",
		"color": [193, 85, 185, 255],
		"falling": true
	},
	"magenta_glazed_terracotta": {
		"name": "Magenta Glazed Terracotta",
		"version": 1120,
		"id": "magenta_glazed_terracotta",
		"color": [210, 109, 193, 255]
	},
	"magenta_shulker_box": {
		"name": "Magenta Shulker Box",
		"version": 1110,
		"id": "magenta_shulker_box",
		"color": [174, 55, 164, 255],
		"tile_entity": true,
		"properties": {
			"facing": "south"
		}
	},
	"magenta_stained_glass": {
		"name": "Magenta Stained Glass",
		"version": 1072,
		"id": "magenta_stained_glass",
		"color": [178, 76, 216, 117]
	},
	"magenta_terracotta": {
		"name": "Magenta Terracotta",
		"version": 1061,
		"id": "magenta_terracotta",
		"color": [150, 88, 109, 255]
	},
	"magenta_wool": {
		"name": "Magenta Wool",
		"version": 1020,
		"id": "magenta_wool",
		"color": [190, 70, 180, 255]
	},
	"magma": {
		"name": "Magma Block",
		"version": 1100,
		"id": "magma_block",
		"color": [157, 75, 35, 255]
	},
	"mangrove_log": {
		"name": "Mangrove Log",
		"version": 1190,
		"id": "mangrove_log",
		"color": [85, 68, 41, 255]
	},
	"mangrove_log_top": {
		"name": "Mangrove Log (Top)",
		"version": 1190,
		"id": "mangrove_log",
		"color": [104, 51, 43, 255],
		"properties": {
			"axis": "z"
		}
	},
	"mangrove_planks": {
		"name": "Mangrove Planks",
		"version": 1190,
		"id": "mangrove_planks",
		"color": [119, 56, 49, 255]
	},
	"mangrove_trapdoor": {
		"name": "Mangrove Trapdoor",
		"version": 1190,
		"id": "mangrove_trapdoor",
		"color": [112, 50, 44, 223],
		"properties": {
			"open": "true"
		}
	},
	"melon_side": {
		"name": "Melon",
		"version": 1080,
		"id": "melon",
		"color": [123, 148, 30, 255]
	},
	"moss_block": {
		"name": "Moss Block",
		"version": 1170,
		"id": "moss_block",
		"color": [90, 111, 46, 255]
	},
	"mossy_cobblestone": {
		"name": "Mossy Cobblestone",
		"version": 1000,
		"id": "mossy_cobblestone",
		"color": [113, 121, 101, 255]
	},
	"mossy_stone_bricks": {
		"name": "Mossy Stone Bricks",
		"version": 1000,
		"id": "mossy_stone_bricks",
		"color": [117, 122, 109, 255]
	},
	"mud": {
		"name": "Mud",
		"version": 1200,
		"id": "mud",
		"color": [61, 58, 61, 255]
	},
	"mud_bricks": {
		"name": "Mud Bricks",
		"version": 1200,
		"id": "mud_bricks",
		"color": [139, 105, 80, 255]
	},
	"mushroom_block_inside": {
		"name": "Mushroom Block (Inside)",
		"version": 1080,
		"id": "brown_mushroom_block",
		"color": [202, 170, 120, 255],
		"properties": {
			"north": "false",
			"east": "false",
			"south": "false",
			"west": "false",
			"down": "false",
			"up": "false"
		}
	},
	"mushroom_stem": {
		"name": "Mushroom Stem",
		"version": 1080,
		"id": "mushroom_stem",
		"color": [203, 197, 186, 255]
	},
	"mycelium_side": {
		"name": "Mycelium",
		"version": 1000,
		"id": "mycelium",
		"color": [118, 91, 77, 255]
	},
	"nether_bricks": {
		"name": "Nether Bricks",
		"version": 1000,
		"id": "nether_bricks",
		"color": [46, 23, 27, 255]
	},
	"nether_gold_ore": {
		"name": "Nether Gold Ore",
		"version": 1160,
		"id": "nether_gold_ore",
		"color": [124, 74, 47, 255]
	},
	"nether_quartz_ore": {
		"name": "Nether Quartz Ore",
		"version": 1050,
		"id": "nether_quartz_ore",
		"color": [125, 85, 80, 255]
	},
	"nether_wart_block": {
		"name": "Nether Wart Block",
		"version": 1100,
		"id": "nether_wart_block",
		"color": [116, 8, 8, 255]
	},
	"netherite_block": {
		"name": "Block of Netherite",
		"version": 1160,
		"id": "netherite_block",
		"color": [68, 63, 66, 255]
	},
	"netherrack": {
		"name": "Netherrack",
		"version": 1000,
		"id": "netherrack",
		"color": [99, 40, 40, 255]
	},
	"note_block": {
		"name": "Note Block",
		"version": 1000,
		"id": "note_block",
		"color": [96, 62, 43, 255]
	},
	"oak_log": {
		"name": "Oak Log",
		"version": 1000,
		"id": "oak_log",
		"color": [112, 88, 52, 255]
	},
	"oak_log_top": {
		"name": "Oak Log (Top)",
		"version": 1000,
		"id": "oak_log",
		"color": [156, 125, 76, 255],
		"properties": {
			"axis": "z"
		}
	},
	"oak_planks": {
		"name": "Oak Planks",
		"version": 1000,
		"id": "oak_planks",
		"color": [165, 133, 81, 255]
	},
	"oak_trapdoor": {
		"name": "Oak Trapdoor",
		"version": 1080,
		"id": "oak_trapdoor",
		"color": [130, 103, 60, 219],
		"properties": {
			"open": "true"
		}
	},
	"observer_back": {
		"name": "Observer (Back)",
		"version": 1110,
		"id": "observer",
		"color": [77, 76, 76, 255],
		"properties": {
			"facing": "north"
		}
	},
	"observer_front": {
		"name": "Observer",
		"version": 1110,
		"id": "observer",
		"color": [117, 117, 117, 255]
	},
	"observer_side": {
		"name": "Observer (Side)",
		"version": 1110,
		"id": "observer",
		"color": [75, 74, 74, 255],
		"properties": {
			"facing": "east"
		}
	},
	"observer_top": {
		"name": "Observer (Top)",
		"version": 1110,
		"id": "observer",
		"color": [105, 105, 105, 255],
		"properties": {
			"facing": "down"
		}
	},
	"obsidian": {
		"name": "Obsidian",
		"version": 1000,
		"id": "obsidian",
		"color": [23, 16, 35, 255]
	},
	"ochre_froglight_side": {
		"name": "Ochre Froglight",
		"version": 1190,
		"id": "ochre_froglight",
		"color": [246, 235, 187, 255]
	},
	"orange_concrete": {
		"name": "Orange Concrete",
		"version": 1120,
		"id": "orange_concrete",
		"color": [224, 97, 1, 255]
	},
	"orange_concrete_powder": {
		"name": "Orange Concrete Powder",
		"version": 1120,
		"id": "orange_concrete_powder",
		"color": [227, 132, 34, 255],
		"falling": true
	},
	"orange_glazed_terracotta": {
		"name": "Orange Glazed Terracotta",
		"version": 1120,
		"id": "orange_glazed_terracotta",
		"color": [188, 153, 122, 255]
	},
	"orange_shulker_box": {
		"name": "Orange Shulker Box",
		"version": 1110,
		"id": "orange_shulker_box",
		"color": [235, 107, 11, 255],
		"tile_entity": true,
		"properties": {
			"facing": "south"
		}
	},
	"orange_stained_glass": {
		"name": "Orange Stained Glass",
		"version": 1072,
		"id": "orange_stained_glass",
		"color": [216, 127, 51, 117]
	},
	"orange_terracotta": {
		"name": "Orange Terracotta",
		"version": 1061,
		"id": "orange_terracotta",
		"color": [162, 84, 38, 255]
	},
	"orange_wool": {
		"name": "Orange Wool",
		"version": 1020,
		"id": "orange_wool",
		"color": [241, 119, 23, 255]
	},
	"oxidized_chiseled_copper": {
		"name": "Oxidized Chiseled Copper",
		"version": 1210,
		"id": "oxidized_chiseled_copper",
		"color": [85, 164, 134, 255]
	},
	"oxidized_copper": {
		"name": "Oxidized Copper",
		"version": 1170,
		"id": "oxidized_copper",
		"color": [83, 165, 134, 255]
	},
	"oxidized_copper_bulb": {
		"name": "Oxidized Copper Bulb",
		"version": 1210,
		"id": "oxidized_copper_bulb",
		"color": [73, 138, 114, 255]
	},
	"oxidized_copper_bulb_lit": {
		"name": "Oxidized Copper Bulb (Lit)",
		"version": 1210,
		"id": "oxidized_copper_bulb",
		"color": [150, 157, 111, 255],
		"properties": {
			"lit": "true"
		}
	},
	"oxidized_copper_grate": {
		"name": "Oxidized Copper Grate",
		"version": 1210,
		"id": "oxidized_copper_grate",
		"color": [83, 164, 133, 178]
	},
	"oxidized_copper_trapdoor": {
		"name": "Oxidized Copper Trapdoor",
		"version": 1210,
		"id": "oxidized_copper_trapdoor",
		"color": [85, 164, 134, 203],
		"properties": {
			"open": "true"
		}
	},
	"oxidized_cut_copper": {
		"name": "Oxidized Cut Copper",
		"version": 1170,
		"id": "oxidized_cut_copper",
		"color": [81, 156, 129, 255]
	},
	"packed_ice": {
		"name": "Packed Ice",
		"version": 1072,
		"id": "packed_ice",
		"color": [142, 180, 251, 255]
	},
	"packed_mud": {
		"name": "Packed Mud",
		"version": 1190,
		"id": "packed_mud",
		"color": [143, 107, 80, 255]
	},
	"pale_moss_block": {
		"name": "Pale Moss Block",
		"version": 1214,
		"id": "pale_moss_block",
		"color": [108, 114, 106, 255]
	},
	"pale_oak_log": {
		"name": "Pale Oak Log",
		"version": 1214,
		"id": "pale_oak_log",
		"color": [89, 79, 77, 255]
	},
	"pale_oak_log_top": {
		"name": "Pale Oak Log (Top)",
		"version": 1214,
		"id": "pale_oak_log",
		"color": [207, 199, 198, 255],
		"properties": {
			"axis": "z"
		}
	},
	"pale_oak_planks": {
		"name": "Pale Oak Planks",
		"version": 1214,
		"id": "pale_oak_planks",
		"color": [229, 219, 218, 255]
	},
	"pale_oak_trapdoor": {
		"name": "Pale Oak Trapdoor",
		"version": 1214,
		"id": "pale_oak_trapdoor",
		"color": [232, 223, 221, 255],
		"properties": {
			"open": "true"
		}
	},
	"pearlescent_froglight_side": {
		"name": "Pearlescent Froglight",
		"version": 1190,
		"id": "pearlescent_froglight",
		"color": [236, 227, 230, 255]
	},
	"pink_concrete": {
		"name": "Pink Concrete",
		"version": 1120,
		"id": "pink_concrete",
		"color": [214, 101, 143, 255]
	},
	"pink_concrete_powder": {
		"name": "Pink Concrete Powder",
		"version": 1120,
		"id": "pink_concrete_powder",
		"color": [229, 154, 181, 255],
		"falling": true
	},
	"pink_glazed_terracotta": {
		"name": "Pink Glazed Terracotta",
		"version": 1120,
		"id": "pink_glazed_terracotta",
		"color": [236, 158, 183, 255]
	},
	"pink_shulker_box": {
		"name": "Pink Shulker Box",
		"version": 1110,
		"id": "pink_shulker_box",
		"color": [231, 123, 158, 255],
		"tile_entity": true,
		"properties": {
			"facing": "south"
		}
	},
	"pink_stained_glass": {
		"name": "Pink Stained Glass",
		"version": 1072,
		"id": "pink_stained_glass",
		"color": [242, 127, 165, 117]
	},
	"pink_terracotta": {
		"name": "Pink Terracotta",
		"version": 1061,
		"id": "pink_terracotta",
		"color": [162, 78, 79, 255]
	},
	"pink_wool": {
		"name": "Pink Wool",
		"version": 1020,
		"id": "pink_wool",
		"color": [238, 143, 173, 255]
	},
	"piston_top": {
		"name": "Piston",
		"version": 1070,
		"id": "piston",
		"color": [158, 134, 98, 255],
		"properties": {
			"facing": "south"
		}
	},
	"piston_top_sticky": {
		"name": "Sticky Piston",
		"version": 1070,
		"id": "sticky_piston",
		"color": [132, 156, 105, 255],
		"properties": {
			"facing": "south"
		}
	},
	"podzol_side": {
		"name": "Podzol",
		"version": 1072,
		"id": "podzol",
		"color": [127, 91, 61, 255]
	},
	"polished_andesite": {
		"name": "Polished Andesite",
		"version": 1080,
		"id": "polished_andesite",
		"color": [134, 136, 135, 255]
	},
	"polished_basalt_side": {
		"name": "Polished Basalt",
		"version": 1160,
		"id": "polished_basalt",
		"color": [92, 91, 94, 255]
	},
	"polished_basalt_top": {
		"name": "Polished Basalt (1.16)",
		"version": 1160,
		"id": "polished_basalt",
		"color": [102, 102, 103, 255],
		"properties": {
			"axis": "z"
		}
	},
	"polished_blackstone": {
		"name": "Polished Blackstone",
		"version": 1160,
		"id": "polished_blackstone",
		"color": [55, 51, 60, 255]
	},
	"polished_blackstone_bricks": {
		"name": "Polished Blackstone Bricks",
		"version": 1160,
		"id": "polished_blackstone_bricks",
		"color": [50, 46, 54, 255]
	},
	"polished_deepslate": {
		"name": "Polished Deepslate",
		"version": 1170,
		"id": "polished_deepslate",
		"color": [75, 75, 76, 255]
	},
	"polished_diorite": {
		"name": "Polished Diorite",
		"version": 1080,
		"id": "polished_diorite",
		"color": [196, 196, 197, 255]
	},
	"polished_granite": {
		"name": "Polished Granite",
		"version": 1080,
		"id": "polished_granite",
		"color": [156, 109, 91, 255]
	},
	"polished_tuff": {
		"name": "Polished Tuff",
		"version": 1170,
		"id": "polished_tuff",
		"color": [99, 105, 101, 255]
	},
	"powder_snow": {
		"name": "Powder Snow",
		"version": 1170,
		"id": "powder_snow",
		"color": [248, 253, 253, 255]
	},
	"prismarine": {
		"name": "Prismarine",
		"version": 1080,
		"id": "prismarine",
		"color": [103, 164, 149, 255]
	},
	"prismarine_bricks": {
		"name": "Prismarine Bricks",
		"version": 1080,
		"id": "prismarine_bricks",
		"color": [102, 173, 161, 255]
	},
	"pumpkin_side": {
		"name": "Pumpkin",
		"version": 1130,
		"id": "pumpkin",
		"color": [199, 118, 28, 255]
	},
	"purple_concrete": {
		"name": "Purple Concrete",
		"version": 1120,
		"id": "purple_concrete",
		"color": [100, 32, 156, 255]
	},
	"purple_concrete_powder": {
		"name": "Purple Concrete Powder",
		"version": 1120,
		"id": "purple_concrete_powder",
		"color": [132, 56, 178, 255],
		"falling": true
	},
	"purple_glazed_terracotta": {
		"name": "Purple Glazed Terracotta",
		"version": 1120,
		"id": "purple_glazed_terracotta",
		"color": [117, 50, 163, 255]
	},
	"purple_shulker_box": {
		"name": "Purple Shulker Box",
		"version": 1110,
		"id": "purple_shulker_box",
		"color": [104, 33, 157, 255],
		"tile_entity": true,
		"properties": {
			"facing": "south"
		}
	},
	"purple_stained_glass": {
		"name": "Purple Stained Glass",
		"version": 1072,
		"id": "purple_stained_glass",
		"color": [127, 63, 178, 117]
	},
	"purple_terracotta": {
		"name": "Purple Terracotta",
		"version": 1061,
		"id": "purple_terracotta",
		"color": [118, 70, 86, 255]
	},
	"purple_wool": {
		"name": "Purple Wool",
		"version": 1020,
		"id": "purple_wool",
		"color": [123, 43, 173, 255]
	},
	"purpur_block": {
		"name": "Purpur Block",
		"version": 1090,
		"id": "purpur_block",
		"color": [171, 127, 170, 255]
	},
	"purpur_pillar": {
		"name": "Purpur Pillar",
		"version": 1090,
		"id": "purpur_pillar",
		"color": [173, 131, 172, 255]
	},
	"quartz_block_side": {
		"name": "Block of Quartz",
		"version": 1050,
		"id": "quartz_block",
		"color": [236, 230, 223, 255]
	},
	"quartz_bricks": {
		"name": "Quartz Bricks",
		"version": 1160,
		"id": "quartz_bricks",
		"color": [235, 229, 222, 255]
	},
	"quartz_pillar": {
		"name": "Quartz Pillar",
		"version": 1050,
		"id": "quartz_pillar",
		"color": [236, 231, 224, 255]
	},
	"raw_copper_block": {
		"name": "Block of Raw Copper",
		"version": 1170,
		"id": "raw_copper_block",
		"color": [161, 109, 82, 255]
	},
	"raw_gold_block": {
		"name": "Block of Raw Gold",
		"version": 1170,
		"id": "raw_gold_block",
		"color": [224, 175, 59, 255]
	},
	"raw_iron_block": {
		"name": "Block of Raw Iron",
		"version": 1170,
		"id": "raw_iron_block",
		"color": [171, 140, 114, 255]
	},
	"red_concrete": {
		"name": "Red Concrete",
		"version": 1120,
		"id": "red_concrete",
		"color": [142, 33, 33, 255]
	},
	"red_concrete_powder": {
		"name": "Red Concrete Powder",
		"version": 1120,
		"id": "red_concrete_powder",
		"color": [168, 54, 51, 255],
		"falling": true
	},
	"red_glazed_terracotta": {
		"name": "Red Glazed Terracotta",
		"version": 1120,
		"id": "red_glazed_terracotta",
		"color": [184, 66, 58, 255]
	},
	"red_mushroom_block": {
		"name": "Red Mushroom Block",
		"version": 1080,
		"id": "red_mushroom_block",
		"color": [201, 55, 53, 255]
	},
	"red_nether_bricks": {
		"name": "Red Nether Bricks",
		"version": 1100,
		"id": "red_nether_bricks",
		"color": [73, 10, 12, 255]
	},
	"red_sand": {
		"name": "Red Sand",
		"version": 1072,
		"id": "red_sand",
		"color": [191, 103, 33, 255],
		"falling": true
	},
	"red_sandstone": {
		"name": "Red Sandstone",
		"version": 1072,
		"id": "red_sandstone",
		"color": [188, 100, 31, 255]
	},
	"red_shulker_box": {
		"name": "Red Shulker Box",
		"version": 1110,
		"id": "red_shulker_box",
		"color": [141, 32, 30, 255],
		"tile_entity": true,
		"properties": {
			"facing": "south"
		}
	},
	"red_stained_glass": {
		"name": "Red Stained Glass",
		"version": 1072,
		"id": "red_stained_glass",
		"color": [153, 51, 51, 117]
	},
	"red_terracotta": {
		"name": "Red Terracotta",
		"version": 1061,
		"id": "red_terracotta",
		"color": [143, 61, 47, 255]
	},
	"red_wool": {
		"name": "Red Wool",
		"version": 1020,
		"id": "red_wool",
		"color": [161, 40, 35, 255]
	},
	"redstone_block": {
		"name": "Block of Redstone",
		"version": 1050,
		"id": "redstone_block",
		"color": [180, 26, 6, 255]
	},
	"redstone_lamp": {
		"name": "Redstone Lamp",
		"version": 1021,
		"id": "redstone_lamp",
		"color": [105, 61, 33, 255]
	},
	"redstone_ore": {
		"name": "Redstone Ore",
		"version": 1000,
		"id": "redstone_ore",
		"color": [146, 116, 116, 255]
	},
	"reinforced_deepslate_side": {
		"name": "Reinforced Deepslate",
		"version": 1190,
		"id": "reinforced_deepslate",
		"color": [115, 122, 108, 255],
		"creative": true
	},
	"repeating_command_block_front": {
		"name": "Repeating Command Block",
		"version": 1042,
		"id": "repeating_command_block",
		"color": [135, 120, 181, 255],
		"creative": true,
		"properties": {
			"facing": "south"
		}
	},
	"resin_block": {
		"name": "Block of Resin",
		"version": 1214,
		"id": "resin_block",
		"color": [218, 104, 30, 255]
	},
	"resin_bricks": {
		"name": "Resin Bricks",
		"version": 1214,
		"id": "resin_bricks",
		"color": [207, 94, 29, 255]
	},
	"respawn_anchor_side0": {
		"name": "Respawn Anchor",
		"version": 1160,
		"id": "respawn_anchor",
		"color": [50, 32, 80, 255]
	},
	"rooted_dirt": {
		"name": "Rooted Dirt",
		"version": 1170,
		"id": "rooted_dirt",
		"color": [147, 107, 81, 255]
	},
	"sand": {
		"name": "Sand",
		"version": 1000,
		"id": "sand",
		"color": [219, 207, 164, 255],
		"falling": true
	},
	"sandstone": {
		"name": "Sandstone",
		"version": 1000,
		"id": "sandstone",
		"color": [217, 204, 158, 255]
	},
	"sculk_catalyst_side": {
		"name": "Sculk Catalyst",
		"version": 1190,
		"id": "sculk_catalyst",
		"color": [103, 116, 105, 255]
	},
	"sea_lantern": {
		"name": "Sea Lantern",
		"version": 1080,
		"id": "sea_lantern",
		"color": [182, 204, 196, 255]
	},
	"shroomlight": {
		"name": "Shroomlight",
		"version": 1160,
		"id": "shroomlight",
		"color": [242, 155, 91, 255]
	},
	"shulker_box": {
		"name": "Shulker Box",
		"version": 1110,
		"id": "shulker_box",
		"color": [140, 97, 140, 255],
		"tile_entity": true,
		"properties": {
			"facing": "south"
		}
	},
	"slime_block": {
		"name": "Slime Block",
		"version": 1080,
		"id": "slime_block",
		"color": [112, 192, 92, 180]
	},
	"smithing_table_front": {
		"name": "Smithing Table",
		"version": 1140,
		"id": "smithing_table",
		"color": [62, 41, 44, 255]
	},
	"smoker_front": {
		"name": "Smoker",
		"version": 1140,
		"id": "smoker",
		"color": [97, 84, 70, 255],
		"properties": {
			"facing": "south"
		}
	},
	"smoker_side": {
		"name": "Smoker (Side)",
		"version": 1140,
		"id": "smoker",
		"color": [106, 96, 85, 255]
	},
	"smooth_basalt": {
		"name": "Smooth Basalt",
		"version": 1170,
		"id": "smooth_basalt",
		"color": [75, 74, 79, 255]
	},
	"smooth_stone": {
		"name": "Smooth Stone",
		"version": 1000,
		"id": "smooth_stone",
		"color": [160, 160, 160, 255]
	},
	"smooth_stone_slab_side": {
		"name": "Smooth Stone Slab",
		"version": 1140,
		"id": "smooth_stone_slab",
		"color": [169, 169, 169, 255],
		"properties": {
			"type": "double"
		}
	},
	"snow": {
		"name": "Snow Block",
		"version": 1000,
		"id": "snow_block",
		"color": [249, 254, 254, 255]
	},
	"soul_sand": {
		"name": "Soul Sand",
		"version": 1000,
		"id": "soul_sand",
		"color": [84, 64, 53, 255]
	},
	"soul_soil": {
		"name": "Soul Soil",
		"version": 1160,
		"id": "soul_soil",
		"color": [77, 59, 48, 255]
	},
	"spawner": {
		"name": "Monster Spawner",
		"version": 1000,
		"id": "spawner",
		"color": [39, 51, 67, 175]
	},
	"sponge": {
		"name": "Sponge",
		"version": 1000,
		"id": "sponge",
		"color": [197, 194, 75, 255]
	},
	"spruce_log": {
		"name": "Spruce Log",
		"version": 1000,
		"id": "spruce_log",
		"color": [60, 39, 18, 255]
	},
	"spruce_log_top": {
		"name": "Spruce Log (Top)",
		"version": 1000,
		"id": "spruce_log",
		"color": [111, 82, 48, 255],
		"properties": {
			"axis": "z"
		}
	},
	"spruce_planks": {
		"name": "Spruce Planks",
		"version": 1000,
		"id": "spruce_planks",
		"color": [116, 86, 49, 255]
	},
	"spruce_trapdoor": {
		"name": "Spruce Trapdoor",
		"version": 1130,
		"id": "spruce_trapdoor",
		"color": [105, 80, 50, 255],
		"properties": {
			"open": "true"
		}
	},
	"stone": {
		"name": "Stone",
		"version": 1000,
		"id": "stone",
		"color": [126, 126, 126, 255]
	},
	"stone_bricks": {
		"name": "Stone Bricks",
		"version": 1000,
		"id": "stone_bricks",
		"color": [124, 123, 124, 255]
	},
	"stripped_acacia_log": {
		"name": "Stripped Acacia Log",
		"version": 1130,
		"id": "stripped_acacia_log",
		"color": [175, 93, 60, 255]
	},
	"stripped_acacia_log_top": {
		"name": "Stripped Acacia Log (Top)",
		"version": 1130,
		"id": "stripped_acacia_log",
		"color": [167, 91, 52, 255],
		"properties": {
			"axis": "z"
		}
	},
	"stripped_bamboo_block": {
		"name": "Block of Stripped Bamboo",
		"version": 1200,
		"id": "stripped_bamboo_block",
		"color": [195, 175, 82, 255]
	},
	"stripped_bamboo_block_top": {
		"name": "Block of Stripped Bamboo (Top)",
		"version": 1200,
		"id": "stripped_bamboo_block",
		"color": [183, 163, 77, 255],
		"properties": {
			"axis": "z"
		}
	},
	"stripped_birch_log": {
		"name": "Stripped Birch Log",
		"version": 1130,
		"id": "stripped_birch_log",
		"color": [197, 176, 119, 255]
	},
	"stripped_birch_log_top": {
		"name": "Stripped Birch Log (Top)",
		"version": 1130,
		"id": "stripped_birch_log",
		"color": [192, 173, 117, 255],
		"properties": {
			"axis": "z"
		}
	},
	"stripped_cherry_log": {
		"name": "Stripped Cherry Log",
		"version": 1200,
		"id": "stripped_cherry_log",
		"color": [215, 145, 149, 255]
	},
	"stripped_cherry_log_top": {
		"name": "Stripped Cherry Log (Top)",
		"version": 1200,
		"id": "stripped_cherry_log",
		"color": [221, 166, 159, 255],
		"properties": {
			"axis": "z"
		}
	},
	"stripped_crimson_stem": {
		"name": "Stripped Crimson Stem",
		"version": 1160,
		"id": "stripped_crimson_stem",
		"color": [138, 58, 90, 255]
	},
	"stripped_crimson_stem_top": {
		"name": "Stripped Crimson Stem (Top)",
		"version": 1160,
		"id": "stripped_crimson_stem",
		"color": [123, 57, 83, 255],
		"properties": {
			"axis": "z"
		}
	},
	"stripped_dark_oak_log": {
		"name": "Stripped Dark Oak Log",
		"version": 1130,
		"id": "stripped_dark_oak_log",
		"color": [73, 57, 36, 255]
	},
	"stripped_dark_oak_log_top": {
		"name": "Stripped Dark Oak Log (Top)",
		"version": 1130,
		"id": "stripped_dark_oak_log",
		"color": [67, 45, 23, 255],
		"properties": {
			"axis": "z"
		}
	},
	"stripped_jungle_log": {
		"name": "Stripped Jungle Log",
		"version": 1130,
		"id": "stripped_jungle_log",
		"color": [172, 133, 85, 255]
	},
	"stripped_jungle_log_top": {
		"name": "Stripped Jungle Log (Top)",
		"version": 1130,
		"id": "stripped_jungle_log",
		"color": [166, 123, 83, 255],
		"properties": {
			"axis": "z"
		}
	},
	"stripped_mangrove_log": {
		"name": "Stripped Mangrove Log",
		"version": 1190,
		"id": "stripped_mangrove_log",
		"color": [120, 55, 48, 255]
	},
	"stripped_mangrove_log_top": {
		"name": "Stripped Mangrove Log (Top)",
		"version": 1190,
		"id": "stripped_mangrove_log",
		"color": [109, 45, 44, 255],
		"properties": {
			"axis": "z"
		}
	},
	"stripped_oak_log": {
		"name": "Stripped Oak Log",
		"version": 1130,
		"id": "stripped_oak_log",
		"color": [178, 145, 87, 255]
	},
	"stripped_oak_log_top": {
		"name": "Stripped Oak Log (Top)",
		"version": 1130,
		"id": "stripped_oak_log",
		"color": [162, 131, 78, 255],
		"properties": {
			"axis": "z"
		}
	},
	"stripped_pale_oak_log": {
		"name": "Stripped Pale Oak Log",
		"version": 1214,
		"id": "stripped_pale_oak_log",
		"color": [246, 238, 237, 255]
	},
	"stripped_pale_oak_log_top": {
		"name": "Stripped Pale Oak Log (Top)",
		"version": 1214,
		"id": "stripped_pale_oak_log",
		"color": [236, 228, 226, 255],
		"properties": {
			"axis": "z"
		}
	},
	"stripped_spruce_log": {
		"name": "Stripped Spruce Log",
		"version": 1130,
		"id": "stripped_spruce_log",
		"color": [116, 90, 53, 255]
	},
	"stripped_spruce_log_top": {
		"name": "Stripped Spruce Log (Top)",
		"version": 1130,
		"id": "stripped_spruce_log",
		"color": [109, 82, 48, 255],
		"properties": {
			"axis": "z"
		}
	},
	"stripped_warped_stem": {
		"name": "Stripped Warped Stem",
		"version": 1160,
		"id": "stripped_warped_stem",
		"color": [58, 151, 148, 255]
	},
	"stripped_warped_stem_top": {
		"name": "Stripped Warped Stem (Top)",
		"version": 1160,
		"id": "stripped_warped_stem",
		"color": [53, 130, 126, 255],
		"properties": {
			"axis": "z"
		}
	},
	"structure_block_load": {
		"name": "Structure Block",
		"version": 1090,
		"id": "structure_block",
		"color": [117, 98, 117, 255],
		"creative": true
	},
	"suspicious_gravel_0": {
		"name": "Suspicious Gravel",
		"version": 1200,
		"id": "suspicious_gravel",
		"color": [131, 127, 126, 255],
		"falling": true,
		"creative": true
	},
	"suspicious_sand_0": {
		"name": "Suspicious Sand",
		"version": 1200,
		"id": "suspicious_sand",
		"color": [218, 205, 160, 255],
		"falling": true,
		"creative": true
	},
	"target_side": {
		"name": "Target",
		"version": 1160,
		"id": "target",
		"color": [230, 196, 187, 255]
	},
	"terracotta": {
		"name": "Terracotta",
		"version": 1061,
		"id": "terracotta",
		"color": [152, 94, 68, 255]
	},
	"tinted_glass": {
		"name": "Tinted Glass",
		"version": 1170,
		"id": "tinted_glass",
		"color": [45, 39, 48, 131]
	},
	"tnt_side": {
		"name": "TNT",
		"version": 1000,
		"id": "tnt",
		"color": [189, 118, 117, 255]
	},
	"trial_spawner_side_inactive": {
		"name": "Trial Spawner",
		"version": 1210,
		"id": "trial_spawner",
		"color": [56, 76, 90, 193],
		"creative": true
	},
	"tube_coral_block": {
		"name": "Tube Coral Block",
		"version": 1130,
		"id": "tube_coral_block",
		"color": [51, 90, 209, 255],
		"creative": true
	},
	"tuff": {
		"name": "Tuff",
		"version": 1170,
		"id": "tuff",
		"color": [110, 111, 105, 255]
	},
	"tuff_bricks": {
		"name": "Tuff Bricks",
		"version": 1210,
		"id": "tuff_bricks",
		"color": [101, 105, 98, 255]
	},
	"verdant_froglight_side": {
		"name": "Verdant Froglight",
		"version": 1190,
		"id": "verdant_froglight",
		"color": [214, 236, 212, 255]
	},
	"warped_nylium_side": {
		"name": "Warped Nylium",
		"version": 1160,
		"id": "warped_nylium",
		"color": [80, 74, 69, 255],
		"creative": true
	},
	"warped_planks": {
		"name": "Warped Planks",
		"version": 1160,
		"id": "warped_planks",
		"color": [45, 109, 103, 255]
	},
	"warped_stem": {
		"name": "Warped Stem",
		"version": 1160,
		"id": "warped_stem",
		"color": [63, 68, 81, 255]
	},
	"warped_stem_top": {
		"name": "Warped Stem (Top)",
		"version": 1160,
		"id": "warped_stem",
		"color": [55, 116, 114, 255],
		"properties": {
			"axis": "z"
		}
	},
	"warped_trapdoor": {
		"name": "Warped Trapdoor",
		"version": 1160,
		"id": "warped_trapdoor",
		"color": [48, 122, 115, 200],
		"properties": {
			"open": "true"
		}
	},
	"warped_wart_block": {
		"name": "Warped Wart Block",
		"version": 1160,
		"id": "warped_wart_block",
		"color": [23, 121, 122, 255]
	},
	"weathered_chiseled_copper": {
		"name": "Weathered Chiseled Copper",
		"version": 1210,
		"id": "weathered_chiseled_copper",
		"color": [106, 153, 114, 255]
	},
	"weathered_copper": {
		"name": "Weathered Copper",
		"version": 1170,
		"id": "weathered_copper",
		"color": [109, 154, 113, 255]
	},
	"weathered_copper_bulb": {
		"name": "Weathered Copper Bulb",
		"version": 1210,
		"id": "weathered_copper_bulb",
		"color": [95, 131, 103, 255]
	},
	"weathered_copper_bulb_lit": {
		"name": "Weathered Copper Bulb (Lit)",
		"version": 1210,
		"id": "weathered_copper_bulb",
		"color": [169, 160, 103, 255],
		"properties": {
			"lit": "true"
		}
	},
	"weathered_copper_grate": {
		"name": "Weathered Copper Grate",
		"version": 1210,
		"id": "weathered_copper_grate",
		"color": [107, 154, 113, 178]
	},
	"weathered_copper_trapdoor": {
		"name": "Weathered Copper Trapdoor",
		"version": 1210,
		"id": "weathered_copper_trapdoor",
		"color": [110, 155, 113, 203],
		"properties": {
			"open": "true"
		}
	},
	"weathered_cut_copper": {
		"name": "Weathered Cut Copper",
		"version": 1170,
		"id": "weathered_cut_copper",
		"color": [111, 147, 110, 255]
	},
	"wet_sponge": {
		"name": "Wet Sponge",
		"version": 1000,
		"id": "wet_sponge",
		"color": [173, 182, 71, 255]
	},
	"white_concrete": {
		"name": "White Concrete",
		"version": 1120,
		"id": "white_concrete",
		"color": [207, 213, 214, 255]
	},
	"white_concrete_powder": {
		"name": "White Concrete Powder",
		"version": 1120,
		"id": "white_concrete_powder",
		"color": [226, 228, 228, 255],
		"falling": true
	},
	"white_glazed_terracotta": {
		"name": "White Glazed Terracotta",
		"version": 1120,
		"id": "white_glazed_terracotta",
		"color": [209, 218, 213, 255]
	},
	"white_shulker_box": {
		"name": "White Shulker Box",
		"version": 1110,
		"id": "white_shulker_box",
		"color": [216, 221, 222, 255],
		"tile_entity": true,
		"properties": {
			"facing": "south"
		}
	},
	"white_stained_glass": {
		"name": "White Stained Glass",
		"version": 1072,
		"id": "white_stained_glass",
		"color": [255, 255, 255, 117]
	},
	"white_terracotta": {
		"name": "White Terracotta",
		"version": 1061,
		"id": "white_terracotta",
		"color": [210, 178, 161, 255]
	},
	"white_wool": {
		"name": "White Wool",
		"version": 1020,
		"id": "white_wool",
		"color": [234, 237, 237, 255]
	},
	"yellow_concrete": {
		"name": "Yellow Concrete",
		"version": 1120,
		"id": "yellow_concrete",
		"color": [241, 175, 21, 255]
	},
	"yellow_concrete_powder": {
		"name": "Yellow Concrete Powder",
		"version": 1120,
		"id": "yellow_concrete_powder",
		"color": [233, 199, 57, 255],
		"falling": true
	},
	"yellow_glazed_terracotta": {
		"name": "Yellow Glazed Terracotta",
		"version": 1120,
		"id": "yellow_glazed_terracotta",
		"color": [237, 197, 109, 255]
	},
	"yellow_shulker_box": {
		"name": "Yellow Shulker Box",
		"version": 1110,
		"id": "yellow_shulker_box",
		"color": [248, 189, 30, 255],
		"tile_entity": true,
		"properties": {
			"facing": "south"
		}
	},
	"yellow_stained_glass": {
		"name": "Yellow Stained Glass",
		"version": 1072,
		"id": "yellow_stained_glass",
		"color": [229, 229, 51, 117]
	},
	"yellow_terracotta": {
		"name": "Yellow Terracotta",
		"version": 1061,
		"id": "yellow_terracotta",
		"color": [186, 133, 35, 255]
	},
	"yellow_wool": {
		"name": "Yellow Wool",
		"version": 1020,
		"id": "yellow_wool",
		"color": [249, 198, 41, 255]
	}
}
